client/__init__.py
client/client.py
client/client_files/__init__.py
client/client_files/add_contact_dialog.py
client/client_files/client_db.py
client/client_files/delete_contact_dialog.py
client/client_files/main_window.py
client/client_files/main_window_ui.py
client/client_files/start_dialog.py
client/client_files/transport.py
client/common/__init__.py
client/common/decos.py
client/common/errors.py
client/common/utils.py
client/common/variables.py
client/logs/__init__.py
client/logs/config_client_log.py
chargaka_messenger_client-0.1.1.dist-info/METADATA
chargaka_messenger_client-0.1.1.dist-info/WHEEL
chargaka_messenger_client-0.1.1.dist-info/top_level.txt
chargaka_messenger_client-0.1.1.dist-info/RECORD
